qcparse/__init__.py
qcparse/cli.py
qcparse/encoders/__init__.py
qcparse/encoders/crest.py
qcparse/encoders/terachem.py
qcparse/exceptions.py
qcparse/main.py
qcparse/models.py
qcparse/parsers/__init__.py
qcparse/parsers/crest.py
qcparse/parsers/terachem.py
qcparse/parsers/utils.py
qcparse/utils.py
qcparse-0.7.5.dist-info/METADATA
qcparse-0.7.5.dist-info/WHEEL
qcparse-0.7.5.dist-info/entry_points.txt
qcparse-0.7.5.dist-info/RECORD
