Metadata-Version: 2.3
Name: qcparse
Version: 0.7.5
Summary: A package for parsing Quantum Chemistry program file outputs into structured qcio data objects.
License: MIT
Author: Colton Hicks
Author-email: github@coltonhicks.com
Requires-Python: >=3.9,<4.0
Classifier: License :: OSI Approved :: MIT License
Classifier: Programming Language :: Python :: 3
Classifier: Programming Language :: Python :: 3.9
Classifier: Programming Language :: Python :: 3.10
Classifier: Programming Language :: Python :: 3.11
Classifier: Programming Language :: Python :: 3.12
Classifier: Programming Language :: Python :: 3.13
Requires-Dist: pydantic (>=2.0.0)
Requires-Dist: qcconst (>=0.1.1,<0.2.0)
Requires-Dist: qcio (>=0.12.1)
Requires-Dist: tomli-w (>=1.0.0,<2.0.0)
Project-URL: Homepage, https://github.com/coltonbh/qcparse
Project-URL: Repository, https://github.com/coltonbh/qcparse
